README
setup.py
gator_tests/__init__.py
gator_tests/daemoncheck.py
gator_tests/modulecheck.py
gator_tests.egg-info/PKG-INFO
gator_tests.egg-info/SOURCES.txt
gator_tests.egg-info/dependency_links.txt
gator_tests.egg-info/entry_points.txt
gator_tests.egg-info/not-zip-safe
gator_tests.egg-info/requires.txt
gator_tests.egg-info/top_level.txt