Metadata-Version: 1.0
Name: gator-tests
Version: 0.2.dev
Summary: Tests for checking the gator module and gator daemon
Home-page: https://code.launchpad.net/~stubbsdm/+junk/gator-tests
Author: David Stubbs
Author-email: david.stubbs2@arm.com
License: GNU GPLv3
Platform: UNKNOWN
Classifier: Development Status :: 3 - Alpha
Classifier: Intended Audience :: Developers
Classifier: License :: OSI Approved :: GNU General Public License (GPL)
Classifier: Operating System :: OS Independent
Classifier: Programming Language :: Python :: 2.6
Classifier: Programming Language :: Python :: 2.7
Classifier: Topic :: Software Development :: Testing
